lean/__init__.py
lean/lean.py
lean/makda.py
makda-0.1.dist-info/METADATA
makda-0.1.dist-info/WHEEL
makda-0.1.dist-info/top_level.txt
makda-0.1.dist-info/RECORD
