Metadata-Version: 2.1
Name: makda
Version: 0.1
Summary: Description of your library
Author: yk2
Author-email: kkwieer@yahoo.com
